Metadata-Version: 2.4
Name: kvcached
Version: 0.1.3
Summary: A KV cache management system that supports on-demand KV cache allocation for LLMs with GPU virtual memory
Author: The kvcached team
License-Expression: Apache-2.0
Project-URL: Homepage, https://github.com/ovg-project/kvcached
Project-URL: Repository, https://github.com/ovg-project/kvcached
Project-URL: Issues, https://github.com/ovg-project/kvcached/issues
Project-URL: Documentation, https://github.com/ovg-project/kvcached#readme
Keywords: llm,kv-cache,gpu-memory,gpu-sharing,machine-learning,pytorch,vllm,sglang,cuda,memory-management
Classifier: Programming Language :: Python :: 3
Classifier: Programming Language :: Python :: 3.9
Classifier: Programming Language :: Python :: 3.10
Classifier: Programming Language :: Python :: 3.11
Classifier: Programming Language :: Python :: 3.12
Classifier: Programming Language :: C++
Classifier: Development Status :: 3 - Alpha
Classifier: Intended Audience :: Developers
Classifier: Intended Audience :: Science/Research
Classifier: Topic :: Scientific/Engineering :: Artificial Intelligence
Classifier: Topic :: Software Development :: Libraries :: Python Modules
Requires-Python: <3.13,>=3.9
License-File: LICENSE
Requires-Dist: numpy>=1.26.0
Requires-Dist: posix_ipc>=1.0
Requires-Dist: wrapt>=1.15
Provides-Extra: dev
Requires-Dist: pre-commit; extra == "dev"
Requires-Dist: setuptools>=64; extra == "dev"
Requires-Dist: wheel; extra == "dev"
Dynamic: license-file
